{
  "projects": [
    {
      "id": 1,
      "title": "Project Alpha",
      "description": "A high-performance web application built with modern technologies.",
      "image": "https://placehold.co/600x400?text=Project+Alpha",
      "githubUrl": "#",
      "liveUrl": "#",
      "technologies": [
        "React",
        "TypeScript",
        "Tailwind"
      ]
    },
    {
      "id": 2,
      "title": "Project Beta",
      "description": "An innovative solution for complex data visualization.",
      "image": "https://placehold.co/600x400?text=Project+Beta",
      "githubUrl": "#",
      "liveUrl": "#",
      "technologies": [
        "Vue",
        "D3.js",
        "Node.js"
      ]
    },
    {
      "id": 3,
      "title": "Project Gamma",
      "description": "Mobile-first approach to e-commerce experiences.",
      "image": "https://placehold.co/600x400?text=Project+Gamma",
      "githubUrl": "#",
      "liveUrl": "#",
      "technologies": [
        "React Native",
        "Firebase"
      ]
    }
  ],
  "multimedia": [
    {
      "title": "Design Concept 1",
      "description": " minimalist brand identity design.",
      "image": "https://placehold.co/600x600?text=Design+1"
    },
    {
      "title": "Design Concept 2",
      "description": "Modern UI interface mockup.",
      "image": "https://placehold.co/600x600?text=Design+2"
    },
    {
      "title": "Design Concept 3",
      "description": "Creative poster art.",
      "image": "https://placehold.co/600x600?text=Design+3"
    }
  ],
  "wip": [
    {
      "id": 1,
      "title": "Secret Project X",
      "description": "Next generation AI-powered tool.",
      "image": "https://placehold.co/600x400?text=WIP+Project",
      "githubUrl": "#",
      "technologies": [
        "Python",
        "TensorFlow",
        "React"
      ]
    }
  ]
}